forgekit/__init__.py
forgekit/forgekit.py
forgekit-1.0.6.dist-info/LICENSE
forgekit-1.0.6.dist-info/METADATA
forgekit-1.0.6.dist-info/WHEEL
forgekit-1.0.6.dist-info/top_level.txt
forgekit-1.0.6.dist-info/RECORD
