Metadata-Version: 2.1
Name: forgekit
Version: 1.0.6
Summary: A collection of handy tools for data handling, visualization, and reporting.
Author: 0xMarc
Author-email: marc@codepwn.win
Project-URL: Source, https://github.com/0xMarcio/forgekit
Project-URL: Bug Tracker, https://github.com/0xMarcio/forgekit/issues
Classifier: Programming Language :: Python :: 3.10
Classifier: Programming Language :: Python :: 3.11
Classifier: Programming Language :: Python :: 3.12
Classifier: Programming Language :: Python :: 3.13
Classifier: License :: OSI Approved :: MIT License
Classifier: Operating System :: OS Independent
Requires-Python: >=3.10
License-File: LICENSE
Requires-Dist: pandas>=2.2.3
Requires-Dist: numpy>=2.1.1
Requires-Dist: matplotlib>=3.9.2
Requires-Dist: plotly>=5.24.1
Requires-Dist: scikit-learn>=1.5.2
Requires-Dist: tabulate2>=1.9.1
